{
    "boxes": [
        {
            "h": 57,
            "id": 29,
            "label": "\u09b8\u09c7\u0987",
            "w": 161,
            "x": 28,
            "y": 2294
        },
        {
            "h": 73,
            "id": 19,
            "label": "\u09a6\u09c7\u09b9",
            "w": 166,
            "x": 33,
            "y": 2430
        },
        {
            "h": 48,
            "id": 43,
            "label": "\u09b8\u09b9",
            "w": 119,
            "x": 51,
            "y": 2155
        },
        {
            "h": 104.2210787101762,
            "id": 73,
            "label": "\u09a6\u09c7\u0996\u09cb",
            "w": 229.61206403335694,
            "x": 67.01051117018069,
            "y": 1868.695670656393
        },
        {
            "h": 53,
            "id": 56,
            "label": "\u099a\u09be\u0981\u09a6",
            "w": 117,
            "x": 57,
            "y": 2030
        },
        {
            "h": 69,
            "id": 4,
            "label": "\u09a4\u09be\u09b0\u09c7",
            "w": 195,
            "x": 57,
            "y": 2581
        },
        {
            "h": 62,
            "id": 96,
            "label": "\u09b6\u09cd\u09b0\u09be\u09ac\u09a8\u09c7",
            "w": 228.02761070168378,
            "x": 66.1429424249375,
            "y": 1627.2607249759556
        },
        {
            "h": 87,
            "id": 217,
            "label": "\u0988\u09b7\u09be\u09a8",
            "w": 260,
            "x": 68,
            "y": 393
        },
        {
            "h": 56,
            "id": 117,
            "label": "\u09b9\u09df\u09c7",
            "w": 128,
            "x": 69,
            "y": 1421
        },
        {
            "h": 90.28029217614032,
            "id": 233,
            "label": "\u09ac\u09b0\u09cd\u09b7\u09be\u09ae\u09c1\u0996\u09b0",
            "w": 377.3716212962666,
            "x": 65.68352137082442,
            "y": 162.85985391192986
        },
        {
            "h": 72,
            "id": 84,
            "label": "\u09a2\u09be\u0995\u09c7",
            "w": 138,
            "x": 72,
            "y": 1757
        },
        {
            "h": 64,
            "id": 204,
            "label": "\u098b\u09a6\u09cd\u09a7",
            "w": 151,
            "x": 73,
            "y": 526
        },
        {
            "h": 60,
            "id": 129,
            "label": "\u09b0\u0999\u09c7\u09b0",
            "w": 179,
            "x": 73,
            "y": 1308
        },
        {
            "h": 64,
            "id": 107,
            "label": "\u09ac\u09b2\u09c7",
            "w": 145,
            "x": 76,
            "y": 1527
        },
        {
            "h": 74,
            "id": 222,
            "label": "\u0986\u09b7\u09be\u09a2\u09bc\u09c7",
            "w": 290,
            "x": 96,
            "y": 310
        },
        {
            "h": 62,
            "id": 140,
            "label": "\u09b9\u09c3\u09a6\u09af\u09bc\u09c7\u09b0",
            "w": 227,
            "x": 100,
            "y": 1209
        },
        {
            "h": 57,
            "id": 194,
            "label": "\u09a1\u09be\u0995",
            "w": 142,
            "x": 111,
            "y": 646
        },
        {
            "h": 76.15947540902097,
            "id": 178,
            "label": "\u098f\u09ac\u0982",
            "w": 147.74938229350067,
            "x": 112.85471071368471,
            "y": 772.9202622954895
        },
        {
            "h": 95,
            "id": 156,
            "label": "\u09b0\u0999\u09a7\u09a8\u09c1",
            "w": 236,
            "x": 127,
            "y": 1003
        },
        {
            "h": 97.43374478866028,
            "id": 163,
            "label": "\u09a6\u09c1\u0983\u0996",
            "w": 172.06384717997463,
            "x": 99.73282982220599,
            "y": 866.5134749745966
        },
        {
            "h": 96,
            "id": 86,
            "label": "\u09ac\u09c3\u09b7\u09cd\u099f\u09bf",
            "w": 147,
            "x": 234,
            "y": 1717
        },
        {
            "h": 66,
            "id": 15,
            "label": "\u099b\u09c7\u09a1\u09bc\u09c7",
            "w": 178,
            "x": 240,
            "y": 2443
        },
        {
            "h": 51,
            "id": 116,
            "label": "\u09af\u09be\u09af\u09bc",
            "w": 126,
            "x": 243,
            "y": 1422
        },
        {
            "h": 68,
            "id": 54,
            "label": "\u0986\u09b2\u09cb\u09af\u09bc",
            "w": 288,
            "x": 244,
            "y": 2037
        },
        {
            "h": 77,
            "id": 28,
            "label": "\u099c\u09b2\u09c7\u09a4\u09c7",
            "w": 258,
            "x": 244,
            "y": 2304
        },
        {
            "h": 57,
            "id": 108,
            "label": "\u09b6\u09be\u09a8\u09cd\u09a4",
            "w": 155,
            "x": 270,
            "y": 1525
        },
        {
            "h": 64,
            "id": 128,
            "label": "\u09ab\u09c1\u09b2\u09c7",
            "w": 180,
            "x": 278,
            "y": 1311
        },
        {
            "h": 98,
            "id": 181,
            "label": "\u09a4\u09be\u09b0\u0987",
            "w": 192,
            "x": 298,
            "y": 757
        },
        {
            "h": 84,
            "id": 206,
            "label": "\u09ac\u09a8\u09ad\u09c2\u09ae\u09bf\u09b0",
            "w": 326,
            "x": 300,
            "y": 517
        },
        {
            "h": 73,
            "id": 3,
            "label": "\u09b8\u09c1\u09b8\u09cd\u09a5",
            "w": 142,
            "x": 309,
            "y": 2585
        },
        {
            "h": 78,
            "id": 101,
            "label": "\u0989\u09a4\u09cd\u09a4\u09b0",
            "w": 192,
            "x": 327,
            "y": 1615
        },
        {
            "h": 81,
            "id": 195,
            "label": "\u09ae\u09be\u099f\u09bf\u09b0",
            "w": 201,
            "x": 339,
            "y": 641
        },
        {
            "h": 108.44508093720285,
            "id": 167,
            "label": "\u09b9\u09a0\u09be\u09ce",
            "w": 215.3839801947224,
            "x": 359.0053134924123,
            "y": 873.6238946187808
        },
        {
            "h": 64,
            "id": 142,
            "label": "\u099a\u099e\u09cd\u099a\u09b2\u09a4\u09be",
            "w": 269,
            "x": 365,
            "y": 1193
        },
        {
            "h": 94.9152792491606,
            "id": 71,
            "label": "\u09a5\u09c7\u09ae\u09c7",
            "w": 192.23347696032533,
            "x": 353.4156371375336,
            "y": 1882.4299403524565
        },
        {
            "h": 72,
            "id": 212,
            "label": "\u0995\u09cb\u09a3\u09c7",
            "w": 227,
            "x": 404,
            "y": 435
        },
        {
            "h": 66,
            "id": 123,
            "label": "\u09a7\u09b0\u09be\u09b0",
            "w": 153,
            "x": 416,
            "y": 1396
        },
        {
            "h": 68,
            "id": 106,
            "label": "\u09ad\u09be\u09ac\u09c7",
            "w": 170,
            "x": 435,
            "y": 1527
        },
        {
            "h": 70,
            "id": 153,
            "label": "\u098f\u09a8\u09c7",
            "w": 158,
            "x": 439,
            "y": 1028
        },
        {
            "h": 66,
            "id": 81,
            "label": "\u09a8\u09be\u09ae\u09c7",
            "w": 182,
            "x": 442,
            "y": 1767
        },
        {
            "h": 65.55988204972324,
            "id": 223,
            "label": "\u0997\u09b2\u09cd\u09aa",
            "w": 169.68440059928366,
            "x": 442.51655276577804,
            "y": 301.3296967528491
        },
        {
            "h": 83,
            "id": 244,
            "label": "\u09a6\u09bf\u09a8",
            "w": 189,
            "x": 476,
            "y": 135
        },
        {
            "h": 70,
            "id": 2,
            "label": "\u0995\u09b0\u09c7",
            "w": 184,
            "x": 493,
            "y": 2595
        },
        {
            "h": 70,
            "id": 13,
            "label": "\u09ae\u09a8\u09c7",
            "w": 149,
            "x": 499,
            "y": 2452
        },
        {
            "h": 69,
            "id": 176,
            "label": "\u09ab\u09be\u0981\u0995\u09c7",
            "w": 217,
            "x": 533,
            "y": 789
        },
        {
            "h": 77,
            "id": 93,
            "label": "\u09aa\u09c2\u09b0\u09cd\u09ac",
            "w": 94,
            "x": 581,
            "y": 1648
        },
        {
            "h": 102,
            "id": 136,
            "label": "\u0995\u09c1\u099c\u09cd\u099d\u099f\u09bf\u0995\u09be",
            "w": 343,
            "x": 585,
            "y": 1269
        },
        {
            "h": 113,
            "id": 31,
            "label": "\u099c\u09c0\u09ac\u0995\u09c1\u09b2\u09c7",
            "w": 318,
            "x": 588,
            "y": 2276
        },
        {
            "h": 69,
            "id": 70,
            "label": "\u0997\u09c7\u099b\u09c7",
            "w": 193,
            "x": 599,
            "y": 1898
        },
        {
            "h": 57,
            "id": 160,
            "label": "\u09af\u09c7\u09a8",
            "w": 156,
            "x": 615,
            "y": 910
        },
        {
            "h": 62,
            "id": 154,
            "label": "\u09a6\u09c7\u09af\u09bc",
            "w": 188,
            "x": 646,
            "y": 1027
        },
        {
            "h": 72.24516709382442,
            "id": 121,
            "label": "\u0985\u0999\u09cd\u0997\u09a8",
            "w": 242.32233129386947,
            "x": 585.1816555360474,
            "y": 1395.171878903946
        },
        {
            "h": 72.76044796214971,
            "id": 189,
            "label": "\u0989\u09aa\u09b0",
            "w": 172.24922374712992,
            "x": 608.0545858366689,
            "y": 665.3518280187175
        },
        {
            "h": 89,
            "id": 205,
            "label": "\u09a8\u09bf\u09b0\u09cd\u099c\u09a8\u09a4\u09be",
            "w": 333,
            "x": 676,
            "y": 517
        },
        {
            "h": 96,
            "id": 85,
            "label": "\u09ae\u09be\u09a0\u09c7",
            "w": 170,
            "x": 677,
            "y": 1737
        },
        {
            "h": 64,
            "id": 141,
            "label": "\u09ac\u09a8\u09cd\u09a7\u09c7",
            "w": 123,
            "x": 678,
            "y": 1200
        },
        {
            "h": 87,
            "id": 224,
            "label": "\u09b6\u09cb\u09a8\u09be\u09a4\u09c7",
            "w": 334,
            "x": 688,
            "y": 303
        },
        {
            "h": 70,
            "id": 241,
            "label": "\u09b6\u09c7\u09b7\u09c7",
            "w": 214,
            "x": 707,
            "y": 153
        },
        {
            "h": 82,
            "id": 98,
            "label": "\u09a6\u09bf\u0995\u09c7",
            "w": 202,
            "x": 710,
            "y": 1635
        },
        {
            "h": 100.03015631485492,
            "id": 12,
            "label": "\u0997\u09bf\u09af\u09bc\u09c7",
            "w": 212.3242646414984,
            "x": 698.9318398744422,
            "y": 2419.0123441612272
        },
        {
            "h": 67,
            "id": 38,
            "label": "\u09af\u09c7",
            "w": 148,
            "x": 758,
            "y": 2188
        },
        {
            "h": 113.97101983164687,
            "id": 53,
            "label": "\u0985\u0982\u09b6\u09c1\u09ae\u09be\u09a8",
            "w": 377.5290031923304,
            "x": 622.5568186524512,
            "y": 2014.9806518869418
        },
        {
            "h": 64,
            "id": 103,
            "label": "\u09ac\u09cd\u09b0\u09b9\u09cd\u09ae\u09be\u09a3\u09cd\u09a1\u09c7",
            "w": 255,
            "x": 789,
            "y": 1532
        },
        {
            "h": 66,
            "id": 177,
            "label": "\u099c\u09ae\u09c7",
            "w": 190,
            "x": 817,
            "y": 787
        },
        {
            "h": 79,
            "id": 188,
            "label": "\u09b6\u09c1\u0995\u09a8\u09cb",
            "w": 280,
            "x": 829,
            "y": 673
        },
        {
            "h": 99,
            "id": 168,
            "label": "\u09ac\u09c3\u09b7\u09cd\u099f\u09bf\u09a4\u09c7",
            "w": 264,
            "x": 829,
            "y": 870
        },
        {
            "h": 85,
            "id": 146,
            "label": "\u09ac\u09cd\u09b0\u09a4\u09c0",
            "w": 146,
            "x": 842,
            "y": 1166
        },
        {
            "h": 80,
            "id": 68,
            "label": "\u09aa\u09be\u09b0\u09be\u09aa\u09be\u09b0\u09c7",
            "w": 318,
            "x": 849,
            "y": 1905
        },
        {
            "h": 93,
            "id": 125,
            "label": "\u0995\u09cd\u09b7\u09bf\u09aa\u09cd\u09a4",
            "w": 158,
            "x": 898,
            "y": 1384
        },
        {
            "h": 116.7175676051411,
            "id": 80,
            "label": "\u098a\u09b7\u09be\u09b0",
            "w": 228.86010303328098,
            "x": 892.5699484833597,
            "y": 1747.1412161974292
        },
        {
            "h": 75,
            "id": 214,
            "label": "\u0985\u09a8\u09cd\u09a7\u0995\u09be\u09b0",
            "w": 325,
            "x": 907,
            "y": 424
        },
        {
            "h": 105.1948424658741,
            "id": 94,
            "label": "\u09b9\u09a0\u09be\u09ce",
            "w": 219.27938992886436,
            "x": 950.2359687366072,
            "y": 1635.6418537911072
        },
        {
            "h": 61,
            "id": 131,
            "label": "\u09aa\u09cd\u09b0\u09ad\u099e\u09cd\u099c\u09a8",
            "w": 263,
            "x": 966,
            "y": 1300
        },
        {
            "h": 74,
            "id": 37,
            "label": "\u099c\u09b2\u09c7\u09a4\u09c7",
            "w": 245,
            "x": 968,
            "y": 2188
        },
        {
            "h": 78,
            "id": 25,
            "label": "\u09ac\u09bf\u09a8\u09be\u09b6",
            "w": 249,
            "x": 983,
            "y": 2313
        },
        {
            "h": 88,
            "id": 18,
            "label": "\u09a7\u09b0\u09c7",
            "w": 152,
            "x": 989,
            "y": 2433
        },
        {
            "h": 61,
            "id": 143,
            "label": "\u09b9\u09b2\u09c7",
            "w": 132,
            "x": 1020,
            "y": 1192
        },
        {
            "h": 86,
            "id": 203,
            "label": "\u099a\u09bf\u09b0\u09c7",
            "w": 173,
            "x": 1048,
            "y": 526
        },
        {
            "h": 149.40862476206766,
            "id": 240,
            "label": "\u098a\u09b0\u09cd\u09a6\u09cd\u09a7\u09aa\u09be\u09a8\u09c7",
            "w": 327.80698268692487,
            "x": 1068.4386173542275,
            "y": 118.79568761896611
        },
        {
            "h": 53,
            "id": 175,
            "label": "\u09a5\u09be\u0995\u09be",
            "w": 194,
            "x": 1076,
            "y": 789
        },
        {
            "h": 70,
            "id": 225,
            "label": "\u09ac\u09b8\u09c7",
            "w": 163,
            "x": 1100,
            "y": 301
        },
        {
            "h": 57,
            "id": 120,
            "label": "\u09b9\u09b2\u09c7",
            "w": 141,
            "x": 1105,
            "y": 1415
        },
        {
            "h": 96,
            "id": 166,
            "label": "\u09a7\u09c1\u09af\u09bc\u09c7",
            "w": 155,
            "x": 1141,
            "y": 886
        },
        {
            "h": 110.85174455335357,
            "id": 49,
            "label": "\u09b8\u09c1\u0996",
            "w": 184.75290758892265,
            "x": 1059.467662659581,
            "y": 2039.0910468219408
        },
        {
            "h": 59,
            "id": 190,
            "label": "\u09aa\u09be\u09a4\u09be",
            "w": 194,
            "x": 1154,
            "y": 664
        },
        {
            "h": 76,
            "id": 79,
            "label": "\u0986\u0995\u09be\u09b6\u09c7",
            "w": 311,
            "x": 1166,
            "y": 1779
        },
        {
            "h": 95,
            "id": 149,
            "label": "\u099c\u09c0\u09ac\u09a8",
            "w": 182,
            "x": 1193,
            "y": 1146
        },
        {
            "h": 54,
            "id": 92,
            "label": "\u099d\u09a1\u09bc",
            "w": 155,
            "x": 1213,
            "y": 1659
        },
        {
            "h": 152.2127439142546,
            "id": 16,
            "label": "\u0994\u09b7\u09a7\u09c7\u09b0",
            "w": 261.0104813343869,
            "x": 1237.2717470832395,
            "y": 2411.2874427773277
        },
        {
            "h": 100,
            "id": 41,
            "label": "\u0988\u09b6\u09cd\u09ac\u09b0",
            "w": 221,
            "x": 1238,
            "y": 2170
        },
        {
            "h": 119.68167365338275,
            "id": 48,
            "label": "\u09a6\u09c1\u0983\u0996",
            "w": 164.80755060465822,
            "x": 1257.9003930544447,
            "y": 2038.6591631733088
        },
        {
            "h": 47,
            "id": 119,
            "label": "\u09b8\u09be\u0999\u09cd\u0997",
            "w": 189,
            "x": 1267,
            "y": 1415
        },
        {
            "h": 64.29265144248897,
            "id": 64,
            "label": "\u0996\u09c7\u09af\u09bc\u09be",
            "w": 186.31747969047834,
            "x": 1230.2547833976666,
            "y": 1911.1072492707406
        },
        {
            "h": 76,
            "id": 26,
            "label": "\u0998\u099f\u09be\u09af\u09bc",
            "w": 252,
            "x": 1284,
            "y": 2312
        },
        {
            "h": 58,
            "id": 132,
            "label": "\u09b6\u0999\u09cd\u0995\u09be\u09b0",
            "w": 223,
            "x": 1285,
            "y": 1298
        },
        {
            "h": 66,
            "id": 213,
            "label": "\u09ae\u09c7\u0998\u09c7\u09b0",
            "w": 211,
            "x": 1298,
            "y": 430
        },
        {
            "h": 104,
            "id": 110,
            "label": "\u09ac\u09be\u099e\u09cd\u099b\u09bf\u09a4\u09ab\u09b2",
            "w": 394,
            "x": 1312,
            "y": 1485
        },
        {
            "h": 54,
            "id": 221,
            "label": "\u0993\u09b8\u09ae\u09be\u09a8",
            "w": 278,
            "x": 1317,
            "y": 314
        },
        {
            "h": 76.50458582849356,
            "id": 200,
            "label": "\u09a5\u09c7\u0995\u09c7",
            "w": 191.26146457123394,
            "x": 1285.935325658002,
            "y": 532.7477070857532
        },
        {
            "h": 68,
            "id": 174,
            "label": "\u09a2\u09c7\u09b0",
            "w": 157,
            "x": 1325,
            "y": 790
        },
        {
            "h": 79,
            "id": 161,
            "label": "\u09ae\u09c1\u099b\u09c7",
            "w": 167,
            "x": 1325,
            "y": 906
        },
        {
            "h": 76,
            "id": 191,
            "label": "\u099d\u09b0\u09c7",
            "w": 132,
            "x": 1389,
            "y": 659
        },
        {
            "h": 104,
            "id": 99,
            "label": "\u0989\u09a0\u09c7",
            "w": 153,
            "x": 1400,
            "y": 1624
        },
        {
            "h": 145.5875666260753,
            "id": 147,
            "label": "\u09aa\u09b0\u09bf\u09aa\u09c2\u09b0\u09cd\u09a3",
            "w": 246.0634928891414,
            "x": 1402.5593744288285,
            "y": 1121.0006791378205
        },
        {
            "h": 82,
            "id": 236,
            "label": "\u099a\u09c7\u09af\u09bc\u09c7",
            "w": 174,
            "x": 1454,
            "y": 172
        },
        {
            "h": 53,
            "id": 122,
            "label": "\u09b9\u09ac\u09c7",
            "w": 141,
            "x": 1488,
            "y": 1407
        },
        {
            "h": 96,
            "id": 55,
            "label": "\u09aa\u09be\u09b6\u09be\u09aa\u09be\u09b6\u09bf",
            "w": 356,
            "x": 1499,
            "y": 2036
        },
        {
            "h": 66,
            "id": 201,
            "label": "\u09b9\u09a4\u09c7",
            "w": 153,
            "x": 1515,
            "y": 540
        },
        {
            "h": 61,
            "id": 78,
            "label": "\u09b8\u09a8\u09cd\u09a7\u09cd\u09af\u09be\u09b0",
            "w": 206,
            "x": 1522,
            "y": 1781
        },
        {
            "h": 77.37393063279342,
            "id": 65,
            "label": "\u09b6\u09b0\u09ce",
            "w": 209.19618282199704,
            "x": 1511.4181143274106,
            "y": 1908.3130346836035
        },
        {
            "h": 128,
            "id": 165,
            "label": "\u09a7\u09c2\u09b8\u09b0",
            "w": 164,
            "x": 1524,
            "y": 887
        },
        {
            "h": 78,
            "id": 180,
            "label": "\u09aa\u09c1\u09b0\u09cb\u09a8\u09cb",
            "w": 289,
            "x": 1530,
            "y": 781
        },
        {
            "h": 70,
            "id": 215,
            "label": "\u0986\u09a1\u09bc\u09ae\u09cd\u09ac\u09b0",
            "w": 265,
            "x": 1546,
            "y": 418
        },
        {
            "h": 80.31390967984628,
            "id": 133,
            "label": "\u0995\u09be\u09b0\u09a3",
            "w": 168.40013319967773,
            "x": 1562.8124648650523,
            "y": 1281.1375076109348
        },
        {
            "h": 78,
            "id": 192,
            "label": "\u09aa\u09a1\u09bc\u09c7",
            "w": 139,
            "x": 1560,
            "y": 656
        },
        {
            "h": 67,
            "id": 11,
            "label": "\u09b8\u09be\u09a7\u09cd\u09af",
            "w": 197,
            "x": 1568,
            "y": 2456
        },
        {
            "h": 48,
            "id": 91,
            "label": "\u0997\u0997\u09a8",
            "w": 190,
            "x": 1608,
            "y": 1661
        },
        {
            "h": 61,
            "id": 24,
            "label": "\u09b0\u09cb\u0997",
            "w": 221,
            "x": 1638,
            "y": 2351
        },
        {
            "h": 122.71127861671972,
            "id": 228,
            "label": "\u09ad\u09c1\u0981\u0987\u099e\u09be",
            "w": 274.71265271540375,
            "x": 1634.546546789211,
            "y": 269.1443606916401
        },
        {
            "h": 83,
            "id": 124,
            "label": "\u09ac\u09bf\u099c\u09cd\u099e\u099c\u09a8\u09c7",
            "w": 335,
            "x": 1664,
            "y": 1385
        },
        {
            "h": 59,
            "id": 145,
            "label": "\u09b9\u09ac\u09c7",
            "w": 133,
            "x": 1675,
            "y": 1179
        },
        {
            "h": 84.45125450949261,
            "id": 202,
            "label": "\u0990\u09b0\u09be\u09ac\u09a4\u09c7\u09b0",
            "w": 328.77283795210434,
            "x": 1725.3393797359552,
            "y": 524.0256447481607
        },
        {
            "h": 84,
            "id": 36,
            "label": "\u09ae\u09c7\u099f\u09be\u09af\u09bc",
            "w": 287,
            "x": 1728,
            "y": 2189
        },
        {
            "h": 110,
            "id": 169,
            "label": "\u099c\u09c0\u09ac\u09a8\u09c7",
            "w": 244,
            "x": 1741,
            "y": 865
        },
        {
            "h": 120.80396700431751,
            "id": 237,
            "label": "\u09af\u0996\u09a8",
            "w": 182.16666854668065,
            "x": 1693.7631553090177,
            "y": 135.5845293992298
        },
        {
            "h": 71,
            "id": 135,
            "label": "\u09b2\u09a3\u09cd\u09a1\u09ad\u09a3\u09cd\u09a1",
            "w": 238,
            "x": 1764,
            "y": 1280
        },
        {
            "h": 62,
            "id": 105,
            "label": "\u09ae\u09c7\u09b2\u09c7",
            "w": 203,
            "x": 1766,
            "y": 1527
        },
        {
            "h": 80,
            "id": 63,
            "label": "\u098b\u09a4\u09c1\u09a4\u09c7",
            "w": 238,
            "x": 1771,
            "y": 1925
        },
        {
            "h": 54,
            "id": 77,
            "label": "\u099b\u09be\u09af\u09bc\u09be",
            "w": 154,
            "x": 1773,
            "y": 1789
        },
        {
            "h": 87,
            "id": 17,
            "label": "\u0995\u09c0",
            "w": 127,
            "x": 1817,
            "y": 2433
        },
        {
            "h": 74,
            "id": 90,
            "label": "\u09ae\u09c7\u0998\u09c7\u09a4\u09c7",
            "w": 238,
            "x": 1837,
            "y": 1661
        },
        {
            "h": 52,
            "id": 144,
            "label": "\u09a8\u09be\u09a8\u09be",
            "w": 169,
            "x": 1838,
            "y": 1181
        },
        {
            "h": 73,
            "id": 216,
            "label": "\u09b8\u09ac\u09c1\u099c\u09c7",
            "w": 217,
            "x": 1860,
            "y": 413
        },
        {
            "h": 95,
            "id": 183,
            "label": "\u0997\u09ad\u09c0\u09b0",
            "w": 194,
            "x": 1864,
            "y": 732
        },
        {
            "h": 104,
            "id": 27,
            "label": "\u09af\u09a6\u09bf",
            "w": 175,
            "x": 1888,
            "y": 2309
        },
        {
            "h": 65,
            "id": 9,
            "label": "\u09ac\u09be",
            "w": 86,
            "x": 1959,
            "y": 2473
        },
        {
            "h": 73,
            "id": 82,
            "label": "\u0990",
            "w": 98,
            "x": 1976,
            "y": 1764
        },
        {
            "h": 84.28322907083937,
            "id": 1668170828553,
            "label": "\u09a4\u0996\u09a8",
            "w": 182.05702491379105,
            "x": 671.2673614645562,
            "y": 421.2031520664852
        },
        {
            "h": 103.79140961778063,
            "id": 1668170917411,
            "label": "\u0994\u09a6\u09be\u09b8\u09c0\u09a8\u09cd\u09af\u09c7",
            "w": 332.1505583749305,
            "x": 1756.050726399356,
            "y": 612.3237492660775
        },
        {
            "h": 84.69967588455503,
            "id": 1668171106546,
            "label": "\u098f",
            "w": 62.169710281908394,
            "x": 668.6355184347286,
            "y": 1506.1338150949182
        },
        {
            "h": 120.11772529654425,
            "id": 1668171266409,
            "label": "\u0985\u09ac\u09b8\u09cd\u09a5\u09be\u09a8",
            "w": 313.1106469079722,
            "x": 201.06629165065058,
            "y": 2115.7853168302163
        },
        {
            "h": 106.57388032148218,
            "id": 1668171280545,
            "label": "\u09a4\u09c3\u09b7\u09cd\u09a3\u09be",
            "w": 172.65466509837802,
            "x": 1532.8742128273047,
            "y": 2186.298835478456
        }
    ],
    "file": "ArifulIslam210637_1.jpg"
}