{
    "boxes": [
        {
            "h": 52,
            "id": 95,
            "label": "\u09b9\u09df\u09c7",
            "w": 159,
            "x": 48,
            "y": 1380
        },
        {
            "h": 70,
            "id": 20,
            "label": "\u0985\u09ac\u09b8\u09cd\u09a5\u09be\u09a8",
            "w": 214,
            "x": 51,
            "y": 2187
        },
        {
            "h": 56,
            "id": 115,
            "label": "\u09b9\u09c3\u09a6\u09af\u09bc\u09c7\u09b0",
            "w": 213,
            "x": 60,
            "y": 1140
        },
        {
            "h": 49,
            "id": 107,
            "label": "\u09a8\u09be\u09a8\u09be",
            "w": 150,
            "x": 60,
            "y": 1259
        },
        {
            "h": 53,
            "id": 80,
            "label": "\u09ac\u09b2\u09c7",
            "w": 140,
            "x": 65,
            "y": 1515
        },
        {
            "h": 131,
            "id": 16,
            "label": "\u099c\u09c0\u09ac\u0995\u09c1\u09b2\u09c7",
            "w": 286,
            "x": 70,
            "y": 2265
        },
        {
            "h": 119,
            "id": 60,
            "label": "\u09ac\u09c3\u09b7\u09cd\u099f\u09bf",
            "w": 180,
            "x": 77,
            "y": 1750
        },
        {
            "h": 157.6236657787633,
            "id": 1,
            "label": "\u0997\u09bf\u09af\u09bc\u09c7",
            "w": 187.65782497750112,
            "x": 26.101044277482696,
            "y": 2409.7745244328225
        },
        {
            "h": 65,
            "id": 43,
            "label": "\u09b8\u09a8\u09cd\u09a7\u09cd\u09af\u09be\u09b0",
            "w": 206,
            "x": 81,
            "y": 1920
        },
        {
            "h": 67,
            "id": 200,
            "label": "\u09ac\u09b0\u09cd\u09b7\u09be\u09ae\u09c1\u0996\u09b0",
            "w": 275,
            "x": 92,
            "y": 187
        },
        {
            "h": 63,
            "id": 126,
            "label": "\u09ae\u09c1\u099b\u09c7",
            "w": 154,
            "x": 93,
            "y": 944
        },
        {
            "h": 63,
            "id": 28,
            "label": "\u098b\u09a4\u09c1\u09a4\u09c7",
            "w": 185,
            "x": 93,
            "y": 2050
        },
        {
            "h": 39,
            "id": 181,
            "label": "\u09a4\u0996\u09a8",
            "w": 170,
            "x": 101,
            "y": 466
        },
        {
            "h": 58,
            "id": 155,
            "label": "\u09b6\u09c1\u0995\u09a8\u09cb",
            "w": 161,
            "x": 101,
            "y": 685
        },
        {
            "h": 43,
            "id": 138,
            "label": "\u09a5\u09be\u0995\u09be",
            "w": 131,
            "x": 102,
            "y": 827
        },
        {
            "h": 76,
            "id": 172,
            "label": "\u09a8\u09bf\u09b0\u09cd\u099c\u09a8\u09a4\u09be",
            "w": 243,
            "x": 104,
            "y": 520
        },
        {
            "h": 92,
            "id": 72,
            "label": "\u0989\u09a4\u09cd\u09a4\u09b0",
            "w": 129,
            "x": 105,
            "y": 1606
        },
        {
            "h": 53,
            "id": 189,
            "label": "\u0997\u09b2\u09cd\u09aa",
            "w": 147,
            "x": 120,
            "y": 334
        },
        {
            "h": 44,
            "id": 94,
            "label": "\u09af\u09be\u09af\u09bc",
            "w": 160,
            "x": 268,
            "y": 1386
        },
        {
            "h": 59,
            "id": 108,
            "label": "\u09b0\u0999\u09c7\u09b0",
            "w": 177,
            "x": 276,
            "y": 1256
        },
        {
            "h": 64,
            "id": 59,
            "label": "\u09a8\u09be\u09ae\u09c7",
            "w": 184,
            "x": 308,
            "y": 1774
        },
        {
            "h": 59,
            "id": 139,
            "label": "\u09a2\u09c7\u09b0",
            "w": 150,
            "x": 311,
            "y": 825
        },
        {
            "h": 63,
            "id": 44,
            "label": "\u099b\u09be\u09af\u09bc\u09be",
            "w": 166,
            "x": 311,
            "y": 1909
        },
        {
            "h": 49,
            "id": 81,
            "label": "\u09b6\u09be\u09a8\u09cd\u09a4",
            "w": 108,
            "x": 316,
            "y": 1502
        },
        {
            "h": 67,
            "id": 29,
            "label": "\u099a\u09be\u0981\u09a6",
            "w": 180,
            "x": 317,
            "y": 2033
        },
        {
            "h": 59,
            "id": 180,
            "label": "\u0985\u09a8\u09cd\u09a7\u0995\u09be\u09b0",
            "w": 242,
            "x": 323,
            "y": 468
        },
        {
            "h": 40,
            "id": 153,
            "label": "\u09aa\u09be\u09a4\u09be",
            "w": 151,
            "x": 324,
            "y": 690
        },
        {
            "h": 90,
            "id": 3,
            "label": "\u09a7\u09b0\u09c7",
            "w": 114,
            "x": 334,
            "y": 2454
        },
        {
            "h": 97,
            "id": 127,
            "label": "\u09a7\u09c2\u09b8\u09b0",
            "w": 156,
            "x": 339,
            "y": 935
        },
        {
            "h": 62,
            "id": 118,
            "label": "\u099a\u099e\u09cd\u099a\u09b2\u09a4\u09be",
            "w": 303,
            "x": 342,
            "y": 1126
        },
        {
            "h": 66,
            "id": 190,
            "label": "\u09b6\u09cb\u09a8\u09be\u09a4\u09c7",
            "w": 259,
            "x": 348,
            "y": 332
        },
        {
            "h": 69,
            "id": 21,
            "label": "\u09af\u09c7",
            "w": 98,
            "x": 355,
            "y": 2184
        },
        {
            "h": 83,
            "id": 70,
            "label": "\u09aa\u09c2\u09b0\u09cd\u09ac",
            "w": 88,
            "x": 377,
            "y": 1614
        },
        {
            "h": 76,
            "id": 203,
            "label": "\u09a6\u09bf\u09a8",
            "w": 115,
            "x": 404,
            "y": 178
        },
        {
            "h": 95,
            "id": 167,
            "label": "\u099a\u09bf\u09b0\u09c7",
            "w": 142,
            "x": 431,
            "y": 541
        },
        {
            "h": 102,
            "id": 15,
            "label": "\u09ac\u09bf\u09a8\u09be\u09b6",
            "w": 225,
            "x": 447,
            "y": 2268
        },
        {
            "h": 57,
            "id": 83,
            "label": "\u09ad\u09be\u09ac\u09c7",
            "w": 169,
            "x": 448,
            "y": 1491
        },
        {
            "h": 82,
            "id": 22,
            "label": "\u099c\u09b2\u09c7\u09a4\u09c7",
            "w": 282,
            "x": 497,
            "y": 2147
        },
        {
            "h": 48,
            "id": 151,
            "label": "\u099d\u09b0\u09c7",
            "w": 143,
            "x": 500,
            "y": 704
        },
        {
            "h": 76,
            "id": 99,
            "label": "\u09a7\u09b0\u09be\u09b0",
            "w": 120,
            "x": 500,
            "y": 1350
        },
        {
            "h": 120,
            "id": 130,
            "label": "\u099c\u09c0\u09ac\u09a8\u09c7",
            "w": 280,
            "x": 527,
            "y": 910
        },
        {
            "h": 62,
            "id": 137,
            "label": "\u09aa\u09c1\u09b0\u09cb\u09a8\u09cb",
            "w": 154,
            "x": 534,
            "y": 828
        },
        {
            "h": 59,
            "id": 110,
            "label": "\u09ab\u09c1\u09b2\u09c7",
            "w": 153.6544917003087,
            "x": 542.5702907446158,
            "y": 1246
        },
        {
            "h": 66,
            "id": 46,
            "label": "\u0990",
            "w": 73,
            "x": 548,
            "y": 1888
        },
        {
            "h": 73,
            "id": 33,
            "label": "\u0986\u09b2\u09cb\u09af\u09bc",
            "w": 248,
            "x": 548,
            "y": 2013
        },
        {
            "h": 80,
            "id": 61,
            "label": "\u09ae\u09be\u09a0\u09c7",
            "w": 172,
            "x": 555,
            "y": 1737
        },
        {
            "h": 99,
            "id": 77,
            "label": "\u09a6\u09bf\u0995\u09c7",
            "w": 136,
            "x": 559,
            "y": 1573
        },
        {
            "h": 100,
            "id": 10,
            "label": "\u0994\u09b7\u09a7\u09c7\u09b0",
            "w": 209,
            "x": 580,
            "y": 2407
        },
        {
            "h": 65.13715007044856,
            "id": 197,
            "label": "\u09b6\u09c7\u09b7\u09c7",
            "w": 219.33938289028595,
            "x": 540.9433840544154,
            "y": 194.44866164005435
        },
        {
            "h": 71,
            "id": 179,
            "label": "\u09ae\u09c7\u0998\u09c7\u09b0",
            "w": 219,
            "x": 622,
            "y": 481
        },
        {
            "h": 63,
            "id": 163,
            "label": "\u09a5\u09c7\u0995\u09c7",
            "w": 202,
            "x": 648,
            "y": 591
        },
        {
            "h": 61,
            "id": 188,
            "label": "\u09ac\u09b8\u09c7",
            "w": 154,
            "x": 653,
            "y": 337
        },
        {
            "h": 72,
            "id": 87,
            "label": "\u098f",
            "w": 53,
            "x": 675,
            "y": 1472
        },
        {
            "h": 43,
            "id": 96,
            "label": "\u0985\u0999\u09cd\u0997\u09a8",
            "w": 186,
            "x": 685,
            "y": 1379
        },
        {
            "h": 53,
            "id": 117,
            "label": "\u09ac\u09a8\u09cd\u09a7\u09c7",
            "w": 181,
            "x": 691,
            "y": 1126
        },
        {
            "h": 74,
            "id": 143,
            "label": "\u0997\u09ad\u09c0\u09b0",
            "w": 159,
            "x": 733,
            "y": 803
        },
        {
            "h": 106,
            "id": 17,
            "label": "\u0998\u099f\u09be\u09af\u09bc",
            "w": 233,
            "x": 742,
            "y": 2239
        },
        {
            "h": 97,
            "id": 114,
            "label": "\u0995\u09c1\u099c\u09cd\u099d\u099f\u09bf\u0995\u09be",
            "w": 308,
            "x": 745,
            "y": 1205
        },
        {
            "h": 74,
            "id": 73,
            "label": "\u09b9\u09a0\u09be\u09ce",
            "w": 149,
            "x": 768,
            "y": 1601
        },
        {
            "h": 68,
            "id": 84,
            "label": "\u09ac\u09cd\u09b0\u09b9\u09cd\u09ae\u09be\u09a3\u09cd\u09a1\u09c7",
            "w": 222,
            "x": 813.4173366755426,
            "y": 1484
        },
        {
            "h": 113.46927434534508,
            "id": 202,
            "label": "\u098a\u09b0\u09cd\u09a6\u09cd\u09a7\u09aa\u09be\u09a8\u09c7",
            "w": 250.6879316932042,
            "x": 845.0926583932003,
            "y": 178.2308894767702
        },
        {
            "h": 98,
            "id": 129,
            "label": "\u09b0\u0999\u09a7\u09a8\u09c1",
            "w": 207,
            "x": 842,
            "y": 932
        },
        {
            "h": 89,
            "id": 24,
            "label": "\u0988\u09b6\u09cd\u09ac\u09b0",
            "w": 180,
            "x": 850,
            "y": 2122
        },
        {
            "h": 89,
            "id": 65,
            "label": "\u098a\u09b7\u09be\u09b0",
            "w": 168,
            "x": 851,
            "y": 1684
        },
        {
            "h": 52,
            "id": 162,
            "label": "\u09b9\u09a4\u09c7",
            "w": 142,
            "x": 867,
            "y": 602
        },
        {
            "h": 109,
            "id": 156,
            "label": "\u0994\u09a6\u09be\u09b8\u09c0\u09a8\u09cd\u09af\u09c7",
            "w": 287,
            "x": 871,
            "y": 673
        },
        {
            "h": 59,
            "id": 177,
            "label": "\u0986\u09a1\u09bc\u09ae\u09cd\u09ac\u09b0",
            "w": 257,
            "x": 884,
            "y": 487
        },
        {
            "h": 70.6770280068651,
            "id": 135,
            "label": "\u09a6\u09c1\u0983\u0996",
            "w": 155.89266812590637,
            "x": 916.5223080786764,
            "y": 823.5145327709245
        },
        {
            "h": 98,
            "id": 121,
            "label": "\u09ac\u09cd\u09b0\u09a4\u09c0",
            "w": 161,
            "x": 908,
            "y": 1078
        },
        {
            "h": 46,
            "id": 185,
            "label": "\u0993\u09b8\u09ae\u09be\u09a8",
            "w": 238,
            "x": 915,
            "y": 351
        },
        {
            "h": 125,
            "id": 11,
            "label": "\u09b8\u09be\u09a7\u09cd\u09af",
            "w": 168,
            "x": 919,
            "y": 2385
        },
        {
            "h": 94,
            "id": 102,
            "label": "\u0995\u09cd\u09b7\u09bf\u09aa\u09cd\u09a4",
            "w": 152,
            "x": 946,
            "y": 1333
        },
        {
            "h": 69.7351386085339,
            "id": 37,
            "label": "\u0985\u0982\u09b6\u09c1\u09ae\u09be\u09a8",
            "w": 234.63658315076066,
            "x": 855.7192432066375,
            "y": 1983.090484485523
        },
        {
            "h": 69,
            "id": 23,
            "label": "\u09a4\u09c3\u09b7\u09cd\u09a3\u09be",
            "w": 155,
            "x": 1073,
            "y": 2137
        },
        {
            "h": 60,
            "id": 119,
            "label": "\u09b9\u09b2\u09c7",
            "w": 183,
            "x": 1077,
            "y": 1114
        },
        {
            "h": 90,
            "id": 128,
            "label": "\u098f\u09a8\u09c7",
            "w": 117.11394418612842,
            "x": 1083.3996862180786,
            "y": 934
        },
        {
            "h": 103,
            "id": 91,
            "label": "\u09ac\u09be\u099e\u09cd\u099b\u09bf\u09a4\u09ab\u09b2",
            "w": 346,
            "x": 1094,
            "y": 1446
        },
        {
            "h": 63,
            "id": 109,
            "label": "\u09aa\u09cd\u09b0\u09ad\u099e\u09cd\u099c\u09a8",
            "w": 236,
            "x": 1095,
            "y": 1251
        },
        {
            "h": 77,
            "id": 164,
            "label": "\u0990\u09b0\u09be\u09ac\u09a4\u09c7\u09b0",
            "w": 285,
            "x": 1097,
            "y": 589
        },
        {
            "h": 61,
            "id": 97,
            "label": "\u09b9\u09b2\u09c7",
            "w": 187,
            "x": 1117,
            "y": 1374
        },
        {
            "h": 72,
            "id": 141,
            "label": "\u09b9\u09a0\u09be\u09ce",
            "w": 130,
            "x": 1177.43448767322,
            "y": 831.646953225643
        },
        {
            "h": 74,
            "id": 36,
            "label": "\u09b8\u09c1\u0996",
            "w": 126,
            "x": 1158,
            "y": 1992
        },
        {
            "h": 65,
            "id": 150,
            "label": "\u098f\u09ac\u0982",
            "w": 120.35236393579936,
            "x": 1199.5504870860598,
            "y": 712.0163927894661
        },
        {
            "h": 73,
            "id": 195,
            "label": "\u099a\u09c7\u09af\u09bc\u09c7",
            "w": 190,
            "x": 1207,
            "y": 218
        },
        {
            "h": 93,
            "id": 79,
            "label": "\u0989\u09a0\u09c7",
            "w": 152,
            "x": 1207,
            "y": 1564
        },
        {
            "h": 64,
            "id": 178,
            "label": "\u09b8\u09ac\u09c1\u099c\u09c7",
            "w": 200,
            "x": 1208,
            "y": 485
        },
        {
            "h": 84,
            "id": 187,
            "label": "\u09ad\u09c1\u0981\u0987\u099e\u09be",
            "w": 230,
            "x": 1216,
            "y": 341
        },
        {
            "h": 98,
            "id": 122,
            "label": "\u099c\u09c0\u09ac\u09a8",
            "w": 213,
            "x": 1272,
            "y": 1060
        },
        {
            "h": 116,
            "id": 18,
            "label": "\u09af\u09a6\u09bf",
            "w": 193,
            "x": 1278,
            "y": 2226
        },
        {
            "h": 54,
            "id": 4,
            "label": "\u09ac\u09be",
            "w": 110,
            "x": 1284,
            "y": 2437
        },
        {
            "h": 105.24438640481586,
            "id": 39,
            "label": "\u09a6\u09c1\u0983\u0996",
            "w": 173.65323756794618,
            "x": 1300.1473153951804,
            "y": 1945.2939143771725
        },
        {
            "h": 51,
            "id": 98,
            "label": "\u09b8\u09be\u0999\u09cd\u0997",
            "w": 153,
            "x": 1316,
            "y": 1361
        },
        {
            "h": 116,
            "id": 27,
            "label": "\u09ae\u09c7\u099f\u09be\u09af\u09bc",
            "w": 159,
            "x": 1320,
            "y": 2081
        },
        {
            "h": 89,
            "id": 154,
            "label": "\u09a4\u09be\u09b0\u0987",
            "w": 161.6097283016152,
            "x": 1350.3603149711626,
            "y": 684.1765233871782
        },
        {
            "h": 53,
            "id": 111,
            "label": "\u09b6\u0999\u09cd\u0995\u09be\u09b0",
            "w": 150,
            "x": 1385,
            "y": 1236
        },
        {
            "h": 55,
            "id": 133,
            "label": "\u09af\u09c7\u09a8",
            "w": 122,
            "x": 1390,
            "y": 851
        },
        {
            "h": 38,
            "id": 160,
            "label": "\u09a1\u09be\u0995",
            "w": 142,
            "x": 1394,
            "y": 621
        },
        {
            "h": 62.15869088126813,
            "id": 194,
            "label": "\u09af\u0996\u09a8",
            "w": 193,
            "x": 1401,
            "y": 208.92065455936597
        },
        {
            "h": 66,
            "id": 6,
            "label": "\u09a4\u09be\u09b0\u09c7",
            "w": 176,
            "x": 1443,
            "y": 2429
        },
        {
            "h": 71.35050053210668,
            "id": 176,
            "label": "\u098b\u09a6\u09cd\u09a7",
            "w": 124.59858163201228,
            "x": 1460.7253432362938,
            "y": 475.91301142753593
        },
        {
            "h": 64,
            "id": 88,
            "label": "\u09ae\u09c7\u09b2\u09c7",
            "w": 159,
            "x": 1473,
            "y": 1464
        },
        {
            "h": 60,
            "id": 100,
            "label": "\u09b9\u09ac\u09c7",
            "w": 161,
            "x": 1493,
            "y": 1349
        },
        {
            "h": 65,
            "id": 13,
            "label": "\u09a6\u09c7\u09b9",
            "w": 126,
            "x": 1515,
            "y": 2285
        },
        {
            "h": 102,
            "id": 142,
            "label": "\u09ac\u09c3\u09b7\u09cd\u099f\u09bf\u09a4\u09c7",
            "w": 227,
            "x": 1516,
            "y": 803
        },
        {
            "h": 76,
            "id": 191,
            "label": "\u0988\u09b7\u09be\u09a8",
            "w": 203,
            "x": 1536,
            "y": 323
        },
        {
            "h": 92,
            "id": 26,
            "label": "\u09b8\u09c7\u0987",
            "w": 126,
            "x": 1557,
            "y": 2105
        },
        {
            "h": 112,
            "id": 123,
            "label": "\u09aa\u09b0\u09bf\u09aa\u09c2\u09b0\u09cd\u09a3",
            "w": 181,
            "x": 1563,
            "y": 1045
        },
        {
            "h": 43,
            "id": 112,
            "label": "\u0995\u09be\u09b0\u09a3",
            "w": 156,
            "x": 1564,
            "y": 1226
        },
        {
            "h": 87,
            "id": 166,
            "label": "\u09ae\u09be\u099f\u09bf\u09b0",
            "w": 217,
            "x": 1585,
            "y": 572
        },
        {
            "h": 72,
            "id": 76,
            "label": "\u09ae\u09c7\u0998\u09c7\u09a4\u09c7",
            "w": 210,
            "x": 1622,
            "y": 1573
        },
        {
            "h": 72,
            "id": 198,
            "label": "\u0986\u09b7\u09be\u09a2\u09bc\u09c7",
            "w": 311,
            "x": 1625,
            "y": 206
        },
        {
            "h": 103,
            "id": 182,
            "label": "\u09ac\u09a8\u09ad\u09c2\u09ae\u09bf\u09b0",
            "w": 286,
            "x": 1639,
            "y": 452
        },
        {
            "h": 65,
            "id": 5,
            "label": "\u09b8\u09c1\u09b8\u09cd\u09a5",
            "w": 119,
            "x": 1642,
            "y": 2435
        },
        {
            "h": 90,
            "id": 103,
            "label": "\u09ac\u09bf\u099c\u09cd\u099e\u099c\u09a8\u09c7",
            "w": 270,
            "x": 1668,
            "y": 1318
        },
        {
            "h": 72,
            "id": 14,
            "label": "\u099b\u09c7\u09a1\u09bc\u09c7",
            "w": 142.44501841340306,
            "x": 1693.2414670747748,
            "y": 2274.482763324721
        },
        {
            "h": 78,
            "id": 25,
            "label": "\u099c\u09b2\u09c7\u09a4\u09c7",
            "w": 247,
            "x": 1718,
            "y": 2121
        },
        {
            "h": 49,
            "id": 146,
            "label": "\u099c\u09ae\u09c7",
            "w": 197,
            "x": 1731,
            "y": 732
        },
        {
            "h": 88.0974715007512,
            "id": 89,
            "label": "\u09b6\u09cd\u09b0\u09be\u09ac\u09a8\u09c7",
            "w": 185.30847453606282,
            "x": 1735.9357663129072,
            "y": 1442.9348714601583
        },
        {
            "h": 50,
            "id": 113,
            "label": "\u09b2\u09a3\u09cd\u09a1\u09ad\u09a3\u09cd\u09a1",
            "w": 208,
            "x": 1763,
            "y": 1210
        },
        {
            "h": 66,
            "id": 120,
            "label": "\u09b9\u09ac\u09c7",
            "w": 172,
            "x": 1770,
            "y": 1089
        },
        {
            "h": 58,
            "id": 7,
            "label": "\u0995\u09b0\u09c7",
            "w": 161,
            "x": 1777,
            "y": 2425
        },
        {
            "h": 62,
            "id": 184,
            "label": "\u0995\u09cb\u09a3\u09c7",
            "w": 165,
            "x": 1781,
            "y": 352
        },
        {
            "h": 98,
            "id": 140,
            "label": "\u09a7\u09c1\u09af\u09bc\u09c7",
            "w": 137,
            "x": 1793,
            "y": 824
        },
        {
            "h": 64,
            "id": 165,
            "label": "\u0989\u09aa\u09b0",
            "w": 135,
            "x": 1811,
            "y": 582
        },
        {
            "h": 50,
            "id": 63,
            "label": "\u0986\u0995\u09be\u09b6\u09c7",
            "w": 191,
            "x": 1826,
            "y": 1694
        },
        {
            "h": 60,
            "id": 78,
            "label": "\u09a2\u09be\u0995\u09c7",
            "w": 159,
            "x": 1838,
            "y": 1565
        },
        {
            "h": 50,
            "id": 58,
            "label": "\u09b6\u09b0\u09ce",
            "w": 117,
            "x": 1865,
            "y": 1823
        },
        {
            "h": 87.41388483206762,
            "id": 1668059937863,
            "label": "\u09b0\u09cb\u0997",
            "w": 139.4346225022083,
            "x": 1095.928891822356,
            "y": 2284.065991317232
        },
        {
            "h": 114.31046478039596,
            "id": 1668059943763,
            "label": "\u0995\u09c0",
            "w": 111.54769800176672,
            "x": 1120.1783913879576,
            "y": 2375.9626394740208
        },
        {
            "h": 67.24144987082083,
            "id": 1668059964362,
            "label": "\u09a6\u09c7\u0996\u09cb",
            "w": 146.70947237188872,
            "x": 710.3618487292932,
            "y": 1882.8586737546675
        },
        {
            "h": 78.44835818262449,
            "id": 1668059968389,
            "label": "\u09a5\u09c7\u09ae\u09c7",
            "w": 146.70947237188872,
            "x": 898.2954703627046,
            "y": 1864.9276204557818
        },
        {
            "h": 71.72421319554229,
            "id": 1668059977270,
            "label": "\u0997\u09c7\u099b\u09c7",
            "w": 167.32154700265008,
            "x": 1106.8411666268767,
            "y": 1846.9965671568962
        },
        {
            "h": 85.17250316970646,
            "id": 1668059987710,
            "label": "\u09aa\u09be\u09b0\u09be\u09aa\u09be\u09b0\u09c7",
            "w": 240.07004569945423,
            "x": 1338.4238874783707,
            "y": 1829.0655138580105
        },
        {
            "h": 116.55184644275647,
            "id": 1668060004118,
            "label": "\u09aa\u09be\u09b6\u09be\u09aa\u09be\u09b6\u09bf",
            "w": 288.56904483065694,
            "x": 1542.7477061650156,
            "y": 1924.6912689165588
        },
        {
            "h": 118.79322810511698,
            "id": 1668060019575,
            "label": "\u09b8\u09b9",
            "w": 153.98432224156892,
            "x": 1850.7163506481538,
            "y": 1931.4154139036414
        },
        {
            "h": 85.17250316970646,
            "id": 1668060059106,
            "label": "\u0997\u0997\u09a8",
            "w": 147.92194735016892,
            "x": 1429.9875331849685,
            "y": 1572.7943479259295
        },
        {
            "h": 67.24144987082104,
            "id": 1668060067833,
            "label": "\u099d\u09a1\u09bc",
            "w": 144.28452241532858,
            "x": 975.3094163299417,
            "y": 1599.690927874258
        },
        {
            "h": 80.689739844985,
            "id": 1668060083001,
            "label": "\u0996\u09c7\u09af\u09bc\u09be",
            "w": 168.53402198093005,
            "x": 1619.13362979666,
            "y": 1823.8290941103278
        },
        {
            "h": 95.58691532053714,
            "id": 1668060166821,
            "label": "\u09ab\u09be\u0981\u0995\u09c7",
            "w": 175.8062596297001,
            "x": 1534.6882621829504,
            "y": 687.6721277061755
        },
        {
            "h": 78.44835818262341,
            "id": 1668060297604,
            "label": "\u09ae\u09a8\u09c7",
            "w": 118.82254787144575,
            "x": 1855.9521516269429,
            "y": 2252.4695839197025
        },
        {
            "h": 92.37703415772492,
            "id": 1668060460637,
            "label": "\u09aa\u09a1\u09bc\u09c7",
            "w": 132.53268122915148,
            "x": 694.1007126781412,
            "y": 684.6625150507367
        },
        {
            "h": 112.45899810505631,
            "id": 1668060554070,
            "label": "\u09a6\u09c7\u09af\u09bc",
            "w": 117.32401289138002,
            "x": 1217.7134368785587,
            "y": 937.6952607871135
        }
    ],
    "file": "TahsinAhmed210601_1.jpg"
}